deciphon_intervals/__init__.py
deciphon_intervals-1.0.0.dist-info/LICENSE
deciphon_intervals-1.0.0.dist-info/METADATA
deciphon_intervals-1.0.0.dist-info/WHEEL
deciphon_intervals-1.0.0.dist-info/RECORD
