Metadata-Version: 2.1
Name: deciphon-intervals
Version: 1.0.0
Summary: It helps to model the Python and R intervals seamlessly.
License: MIT
Author: Danilo Horta
Author-email: danilo.horta@pm.me
Requires-Python: >=3.9,<4.0
Classifier: License :: OSI Approved :: MIT License
Classifier: Programming Language :: Python :: 3
Classifier: Programming Language :: Python :: 3.9
Classifier: Programming Language :: Python :: 3.10
Classifier: Programming Language :: Python :: 3.11
Classifier: Programming Language :: Python :: 3.12
Classifier: Programming Language :: Python :: 3.13
Requires-Dist: pydantic (>=2.7,<3.0)
